{
  "routerMap": [
    {
      "name": "MinePage",
      "pageSourceFile": "src/main/ets/pages/MinePage.ets",
      "buildFunction": "MinePageBuilder"
    },
    {
      "name": "QuickLoginPage",
      "pageSourceFile": "src/main/ets/pages/QuickLoginPage.ets",
      "buildFunction": "QuickLoginPageBuilder"
    },
    {
      "name": "PersonalInformationPage",
      "pageSourceFile": "src/main/ets/pages/PersonalInformationPage.ets",
      "buildFunction": "PersonalInformationPageBuilder"
    },
    {
      "name": "EditNamePage",
      "pageSourceFile": "src/main/ets/pages/EditNamePage.ets",
      "buildFunction": "EditNamePageBuilder"
    }
  ,
    {
      "name": "EditPhonePage",
      "pageSourceFile": "src/main/ets/pages/EditPhonePage.ets",
      "buildFunction": "EditPhonePageBuilder"
    }
  ]
}